[
  {
    "id": "353653ed-048d-4a09-a3dc-4a2ddd58daab",
    "data": [
      {
        "text": "sure",
        "userDefined": false
      }
    ],
    "isTemplate": false,
    "count": 2,
    "updated": 1531858999
  },
  {
    "id": "74c79bf3-7e9b-436d-b459-5858bcd4cc25",
    "data": [
      {
        "text": "okay",
        "userDefined": false
      }
    ],
    "isTemplate": false,
    "count": 1,
    "updated": 1531858999
  },
  {
    "id": "400ee2b9-0962-4342-b870-30cdcc6b9a7e",
    "data": [
      {
        "text": "sounds correct",
        "userDefined": false
      }
    ],
    "isTemplate": false,
    "count": 1,
    "updated": 1531858999
  },
  {
    "id": "d356a8d7-b94b-4277-a9ce-00b2ac126667",
    "data": [
      {
        "text": "that works",
        "userDefined": false
      }
    ],
    "isTemplate": false,
    "count": 0,
    "updated": 1531858999
  },
  {
    "id": "d194540b-8442-4361-bb56-6f20fadf0056",
    "data": [
      {
        "text": "yep that\u0027s ok",
        "userDefined": false
      }
    ],
    "isTemplate": false,
    "count": 0,
    "updated": 1531858999
  },
  {
    "id": "1ec3db0e-a7af-4495-914c-b56b1487f8c8",
    "data": [
      {
        "text": "yes that\u0027s alright",
        "userDefined": false
      }
    ],
    "isTemplate": false,
    "count": 0,
    "updated": 1531867231
  },
  {
    "id": "ce08cd47-6104-4d3d-ada8-c8e5e38971da",
    "data": [
      {
        "text": "I think so",
        "userDefined": false
      }
    ],
    "isTemplate": false,
    "count": 0,
    "updated": 1531858999
  },
  {
    "id": "96c0b315-b6fa-4eb8-a5a0-5105aa584294",
    "data": [
      {
        "text": "sg",
        "userDefined": false
      }
    ],
    "isTemplate": false,
    "count": 0,
    "updated": 1531858999
  },
  {
    "id": "f4bd9014-34a6-41e0-96c4-f952f08eb778",
    "data": [
      {
        "text": "yes I agree",
        "userDefined": false
      }
    ],
    "isTemplate": false,
    "count": 1,
    "updated": 1531858999
  },
  {
    "id": "706028e5-cf79-45ce-adbd-4cb0951aeef9",
    "data": [
      {
        "text": "I don\u0027t mind",
        "userDefined": false
      }
    ],
    "isTemplate": false,
    "count": 3,
    "updated": 1531858999
  },
  {
    "id": "35804add-32a8-481d-ae84-bf09758743cb",
    "data": [
      {
        "text": "I agree",
        "userDefined": false
      }
    ],
    "isTemplate": false,
    "count": 2,
    "updated": 1531858999
  },
  {
    "id": "0d38cc7c-bd1d-4341-b6d3-a9e5d410910a",
    "data": [
      {
        "text": "yes I do",
        "userDefined": false
      }
    ],
    "isTemplate": false,
    "count": 0,
    "updated": 1531858999
  },
  {
    "id": "b0b35d7d-2eb6-425f-804d-744482b048d5",
    "data": [
      {
        "text": "for sure",
        "userDefined": false
      }
    ],
    "isTemplate": false,
    "count": 0,
    "updated": 1531858999
  },
  {
    "id": "032884a6-22e2-466e-9472-61e32c5f33ec",
    "data": [
      {
        "text": "ok",
        "userDefined": false
      }
    ],
    "isTemplate": false,
    "count": 1,
    "updated": 1531858999
  },
  {
    "id": "b894adeb-089f-489b-b124-306c9c90e903",
    "data": [
      {
        "text": "yes that\u0027t ok",
        "userDefined": false
      }
    ],
    "isTemplate": false,
    "count": 0,
    "updated": 1531858999
  },
  {
    "id": "a29805a6-d2c1-4ebb-bf27-015df6d03bf8",
    "data": [
      {
        "text": "that one works",
        "userDefined": false
      }
    ],
    "isTemplate": false,
    "count": 0,
    "updated": 1531858999
  },
  {
    "id": "b802fe98-51b4-4aa7-8aed-40e2d9bd081c",
    "data": [
      {
        "text": "yes you can do it",
        "userDefined": false
      }
    ],
    "isTemplate": false,
    "count": 0,
    "updated": 1531858999
  },
  {
    "id": "ea9c74d9-3b52-446b-b838-4b4f27c7d8c5",
    "data": [
      {
        "text": "perfect",
        "userDefined": false
      }
    ],
    "isTemplate": false,
    "count": 0,
    "updated": 1531858999
  },
  {
    "id": "2bade3b0-3458-46d7-8c43-97b875ec64a9",
    "data": [
      {
        "text": "yes",
        "userDefined": false
      }
    ],
    "isTemplate": false,
    "count": 1,
    "updated": 1531858999
  },
  {
    "id": "24ff1a5b-2d9f-4f8e-8496-f029c9de530f",
    "data": [
      {
        "text": "why not",
        "userDefined": false
      }
    ],
    "isTemplate": false,
    "count": 0,
    "updated": 1531858999
  },
  {
    "id": "64853d5b-4502-40e7-94ca-2b4d4ffe4143",
    "data": [
      {
        "text": "of course",
        "userDefined": false
      }
    ],
    "isTemplate": false,
    "count": 0,
    "updated": 1531858999
  },
  {
    "id": "7cf4df91-cd7a-4121-b714-b2cfe0b478c6",
    "data": [
      {
        "text": "yep that\u0027s right",
        "userDefined": false
      }
    ],
    "isTemplate": false,
    "count": 1,
    "updated": 1531858999
  },
  {
    "id": "1899a8fa-467e-49f8-bc60-7e75bbc46335",
    "data": [
      {
        "text": "okay I will",
        "userDefined": false
      }
    ],
    "isTemplate": false,
    "count": 2,
    "updated": 1531858999
  },
  {
    "id": "6a4944a8-817c-431e-b4a7-4037a3a8d436",
    "data": [
      {
        "text": "exactly",
        "userDefined": false
      }
    ],
    "isTemplate": false,
    "count": 1,
    "updated": 1531858999
  },
  {
    "id": "11fcb888-8a33-4344-9227-409f3ddbffe2",
    "data": [
      {
        "text": "sure why not",
        "userDefined": false
      }
    ],
    "isTemplate": false,
    "count": 0,
    "updated": 1531858999
  },
  {
    "id": "83276487-a3c7-4a6b-b2ef-e1e5b2b5afd3",
    "data": [
      {
        "text": "absolutely",
        "userDefined": false
      }
    ],
    "isTemplate": false,
    "count": 1,
    "updated": 1531858999
  },
  {
    "id": "ef20335d-009d-47cf-8ac7-672a60cae83f",
    "data": [
      {
        "text": "it\u0027s okay",
        "userDefined": false
      }
    ],
    "isTemplate": false,
    "count": 0,
    "updated": 1531858999
  },
  {
    "id": "dcb70ec9-bb17-41b0-b8bb-e4ab624f0f8c",
    "data": [
      {
        "text": "it\u0027s fine",
        "userDefined": false
      }
    ],
    "isTemplate": false,
    "count": 0,
    "updated": 1531858999
  },
  {
    "id": "27de3c6f-b7b7-4972-a344-b08c267a0228",
    "data": [
      {
        "text": "go ahead",
        "userDefined": false
      }
    ],
    "isTemplate": false,
    "count": 1,
    "updated": 1531858999
  },
  {
    "id": "bbc115ac-1ec0-4a16-bc0e-25cc2a5cbac1",
    "data": [
      {
        "text": "confirm",
        "userDefined": false
      }
    ],
    "isTemplate": false,
    "count": 1,
    "updated": 1531858999
  },
  {
    "id": "1915a3c3-e6c9-4616-a359-29eae7d02d04",
    "data": [
      {
        "text": "sounds good",
        "userDefined": false
      }
    ],
    "isTemplate": false,
    "count": 0,
    "updated": 1531858999
  },
  {
    "id": "8543fe7a-b1ec-49f4-9ce4-52726bab38fd",
    "data": [
      {
        "text": "alright",
        "userDefined": false
      }
    ],
    "isTemplate": false,
    "count": 0,
    "updated": 1531858999
  },
  {
    "id": "1ae83ef2-1d04-4a88-b872-c49b1303a151",
    "data": [
      {
        "text": "yeah",
        "userDefined": false
      }
    ],
    "isTemplate": false,
    "count": 0,
    "updated": 1531858999
  },
  {
    "id": "af8f12c4-93ed-4506-9bfd-dace9928ac0a",
    "data": [
      {
        "text": "yup",
        "userDefined": false
      }
    ],
    "isTemplate": false,
    "count": 0,
    "updated": 1531858999
  },
  {
    "id": "db9508fa-08fe-41f1-9d0d-5f02f446aff7",
    "data": [
      {
        "text": "yes please",
        "userDefined": false
      }
    ],
    "isTemplate": false,
    "count": 0,
    "updated": 1531858999
  },
  {
    "id": "a5acd1dd-fc4c-4d52-8da2-fa31f22933f9",
    "data": [
      {
        "text": "do it",
        "userDefined": false
      }
    ],
    "isTemplate": false,
    "count": 1,
    "updated": 1531858999
  },
  {
    "id": "fda0c242-5532-404c-93ae-2acd992727ce",
    "data": [
      {
        "text": "yes I can",
        "userDefined": false
      }
    ],
    "isTemplate": false,
    "count": 0,
    "updated": 1531858999
  },
  {
    "id": "9b0da5fb-a95d-46c4-820d-2b147feef313",
    "data": [
      {
        "text": "it looks perfect",
        "userDefined": false
      }
    ],
    "isTemplate": false,
    "count": 0,
    "updated": 1531858999
  },
  {
    "id": "8a06cd53-d27f-424e-a76c-5131c60a4eb4",
    "data": [
      {
        "text": "that\u0027s correct",
        "userDefined": false
      }
    ],
    "isTemplate": false,
    "count": 0,
    "updated": 1531858999
  },
  {
    "id": "c21acd64-9ae5-40f3-be1e-9f8190d627d2",
    "data": [
      {
        "text": "right",
        "userDefined": false
      }
    ],
    "isTemplate": false,
    "count": 0,
    "updated": 1531858999
  },
  {
    "id": "bd2aab41-e29c-4761-b598-aa524eb722e6",
    "data": [
      {
        "text": "alright why not",
        "userDefined": false
      }
    ],
    "isTemplate": false,
    "count": 0,
    "updated": 1531858999
  },
  {
    "id": "3092e443-3d8c-4065-93f6-c73a6a9169a8",
    "data": [
      {
        "text": "yep",
        "userDefined": false
      }
    ],
    "isTemplate": false,
    "count": 0,
    "updated": 1531858999
  }
]